{
  "info": {
    "_postman_id": "ce2ff0fa-a5e3-490d-870a-4572d331c3a5",
    "name": "SolutionArchitecture",
    "schema": "https://schema.getpostman.com/json/collection/v2.1.0/collection.json",
    "_exporter_id": "49384083",
    "_collection_link": "https://go.postman.co/collection/49384083-ce2ff0fa-a5e3-490d-870a-4572d331c3a5?source=collection_link"
  },
  "item": [
    {
      "name": "Create a order",
      "request": {
        "method": "POST",
        "header": [],
        "body": {
          "mode": "raw",
          "raw": "{\r\n    \"order\": {\r\n        \"customerId\": 1\r\n    },\r\n    \"products\": [\r\n        { \"productId\": 1, \"amount\": 5 },\r\n        { \"productId\": 2, \"amount\": 10 }\r\n    ]\r\n}",
          "options": {
            "raw": {
              "language": "json"
            }
          }
        },
        "url": {
          "raw": "http://localhost:5000/order",
          "protocol": "http",
          "host": [
            "localhost"
          ],
          "port": "5000",
          "path": [
            "order"
          ]
        }
      },
      "response": []
    },
    {
      "name": "Update a order",
      "request": {
        "method": "PUT",
        "header": [],
        "body": {
          "mode": "raw",
          "raw": "{\r\n    \"order\": {\r\n        \"orderId\": 1,\r\n        \"orderStatus\": \"Send\",\r\n        \"customerId\": 1\r\n    },\r\n    \"products\": [\r\n        { \"productId\": 1, \"amount\": 5 },\r\n        { \"productId\": 2, \"amount\": 15 },\r\n        { \"productId\": 3, \"amount\": 10 }\r\n    ]\r\n}",
          "options": {
            "raw": {
              "language": "json"
            }
          }
        },
        "url": {
          "raw": "http://localhost:5000/order",
          "protocol": "http",
          "host": [
            "localhost"
          ],
          "port": "5000",
          "path": [
            "order"
          ]
        }
      },
      "response": []
    },
    {
      "name": "Get a order",
      "request": {
        "method": "GET",
        "header": [],
        "url": {
          "raw": "http://localhost:5000/order/1",
          "protocol": "http",
          "host": [
            "localhost"
          ],
          "port": "5000",
          "path": [
            "order",
            "1"
          ]
        }
      },
      "response": []
    },
    {
      "name": "Delete a order",
      "request": {
        "method": "DELETE",
        "header": [],
        "url": {
          "raw": "http://localhost:5000/order/1",
          "protocol": "http",
          "host": [
            "localhost"
          ],
          "port": "5000",
          "path": [
            "order",
            "1"
          ]
        }
      },
      "response": []
    },
    {
      "name": "Get all logs",
      "request": {
        "method": "GET",
        "header": [],
        "url": {
          "raw": "http://localhost:5000/event",
          "protocol": "http",
          "host": [
            "localhost"
          ],
          "port": "5000",
          "path": [
            "event"
          ]
        }
      },
      "response": []
    },
    {
      "name": "Get external costumer data",
      "request": {
        "method": "GET",
        "header": [],
        "url": {
          "raw": "http://localhost:5000/customerData",
          "protocol": "http",
          "host": [
            "localhost"
          ],
          "port": "5000",
          "path": [
            "customerData"
          ]
        }
      },
      "response": []
    },
    {
      "name": "Create a package",
      "request": {
        "method": "POST",
        "header": [],
        "body": {
          "mode": "raw",
          "raw": "{\r\n    \"orderId\": 2\r\n}",
          "options": {
            "raw": {
              "language": "json"
            }
          }
        },
        "url": {
          "raw": "http://localhost:5100/package",
          "protocol": "http",
          "host": [
            "localhost"
          ],
          "port": "5100",
          "path": [
            "package"
          ]
        }
      },
      "response": []
    }
  ]
}